[{"date":"2025-03-04","symbol":"COMI","open":13.86,"high":14.14,"low":12.9,"close":13.17,"volume":453150,"market":"EGX","exchange":"Egyptian Exchange","asset_type":"stock"},{"date":"2025-03-05","symbol":"COMI","open":13.04,"high":13.3,"low":12.14,"close":12.38,"volume":453150,"market":"EGX","exchange":"Egyptian Exchange","asset_type":"stock"},{"date":"2025-03-06","symbol":"COMI","open":12.26,"high":12.5,"low":11.41,"close":11.65,"volume":453150,"market":"EGX","exchange":"Egyptian Exchange","asset_type":"stock"},{"date":"2025-03-07","symbol":"COMI","open":11.53,"high":11.76,"low":10.73,"close":10.95,"volume":453150,"market":"EGX","exchange":"Egyptian Exchange","asset_type":"stock"},{"date":"2025-03-10","symbol":"COMI","open":10.84,"high":11.06,"low":10.1,"close":10.3,"volume":453150,"market":"EGX","exchange":"Egyptian Exchange","asset_type":"stock"},{"date":"2025-03-11","symbol":"COMI","open":10.2,"high":10.4,"low":9.5,"close":9.69,"volume":453150,"market":"EGX","exchange":"Egyptian Exchange","asset_type":"stock"},{"date":"2025-03-12","symbol":"COMI","open":9.59,"high":9.78,"low":8.93,"close":9.11,"volume":453150,"market":"EGX","exchange":"Egyptian Exchange","asset_type":"stock"},{"date":"2025-03-13","symbol":"COMI","open":9.02,"high":9.2,"low":8.4,"close":8.57,"volume":453150,"market":"EGX","exchange":"Egyptian Exchange","asset_type":"stock"},{"date":"2025-03-14","symbol":"COMI","open":8.48,"high":8.65,"low":7.9,"close":8.06,"volume":453150,"market":"EGX","exchange":"Egyptian Exchange","asset_type":"stock"},{"date":"2025-03-17","symbol":"COMI","open":7.98,"high":8.14,"low":7.43,"close":7.58,"volume":453150,"market":"EGX","exchange":"Egyptian Exchange","asset_type":"stock"},{"date":"2025-03-18","symbol":"COMI","open":7.51,"high":7.66,"low":6.99,"close":7.13,"volume":453150,"market":"EGX","exchange":"Egyptian Exchange","asset_type":"stock"},{"date":"2025-03-19","symbol":"COMI","open":7.06,"high":7.2,"low":6.57,"close":6.71,"volume":453150,"market":"EGX","exchange":"Egyptian Exchange","asset_type":"stock"},{"date":"2025-03-20","symbol":"COMI","open":6.64,"high":6.77,"low":6.18,"close":6.31,"volume":453150,"market":"EGX","exchange":"Egyptian Exchange","asset_type":"stock"},{"date":"2025-03-21","symbol":"COMI","open":6.24,"high":6.37,"low":5.81,"close":5.93,"volume":453150,"market":"EGX","exchange":"Egyptian Exchange","asset_type":"stock"},{"date":"2025-03-24","symbol":"COMI","open":5.87,"high":5.99,"low":5.47,"close":5.58,"volume":453150,"market":"EGX","exchange":"Egyptian Exchange","asset_type":"stock"},{"date":"2025-03-25","symbol":"COMI","open":5.52,"high":5.63,"low":5.14,"close":5.25,"volume":453150,"market":"EGX","exchange":"Egyptian Exchange","asset_type":"stock"},{"date":"2025-03-26","symbol":"COMI","open":5.19,"high":5.3,"low":4.84,"close":4.93,"volume":453150,"market":"EGX","exchange":"Egyptian Exchange","asset_type":"stock"},{"date":"2025-03-27","symbol":"COMI","open":4.88,"high":4.98,"low":4.55,"close":4.64,"volume":453150,"market":"EGX","exchange":"Egyptian Exchange","asset_type":"stock"},{"date":"2025-03-28","symbol":"COMI","open":4.59,"high":4.69,"low":4.28,"close":4.36,"volume":453150,"market":"EGX","exchange":"Egyptian Exchange","asset_type":"stock"},{"date":"2025-03-31","symbol":"COMI","open":4.32,"high":4.41,"low":4.02,"close":4.1,"volume":453150,"market":"EGX","exchange":"Egyptian Exchange","asset_type":"stock"},{"date":"2025-04-01","symbol":"COMI","open":4.06,"high":4.15,"low":3.78,"close":3.86,"volume":453150,"market":"EGX","exchange":"Egyptian Exchange","asset_type":"stock"},{"date":"2025-04-02","symbol":"COMI","open":3.82,"high":3.9,"low":3.56,"close":3.63,"volume":453150,"market":"EGX","exchange":"Egyptian Exchange","asset_type":"stock"},{"date":"2025-04-03","symbol":"COMI","open":3.59,"high":3.67,"low":3.35,"close":3.41,"volume":453150,"market":"EGX","exchange":"Egyptian Exchange","asset_type":"stock"}]